LICENSE
MANIFEST.in
README.md
setup.cfg
setup.py
implicit_sdk/__init__.py
implicit_sdk/django_auth.py
implicit_sdk/doc-templete.html
implicit_sdk/function-template.html
implicit_sdk/function-template.js
implicit_sdk/implicit_endpoint.py
implicit_sdk/module-header.js
implicit_sdk.egg-info/PKG-INFO
implicit_sdk.egg-info/SOURCES.txt
implicit_sdk.egg-info/dependency_links.txt
implicit_sdk.egg-info/requires.txt
implicit_sdk.egg-info/top_level.txt
implicit_sdk/__pycache__/__init__.cpython-310.pyc
implicit_sdk/__pycache__/implicit_endpoint.cpython-310.pyc