Metadata-Version: 2.1
Name: implicit-sdk
Version: 0.1.15
Summary: A new generation for client-server communication.
Home-page: https://github.com/meena-erian/implicit-sdk
Author: Meena (Menas) Erian
Author-email: menas@portacode.com
License: MIT License
Platform: UNKNOWN
Classifier: Environment :: Web Environment
Classifier: Framework :: Django
Classifier: Framework :: Django :: 3.1
Classifier: Framework :: Flask
Classifier: Intended Audience :: Developers
Classifier: License :: OSI Approved :: MIT License
Classifier: Programming Language :: JavaScript
Classifier: Programming Language :: PHP
Classifier: Development Status :: 3 - Alpha
Requires-Python: >=3.6
License-File: LICENSE
